{
  "slug": "morning-brief",
  "date": "2026-03-31",
  "title": "Morning Brief",
  "item_count": 4,
  "last_published": "2026-03-31T12:01:25.750993+00:00",
  "freshness_seconds": 300,
  "items": [
    {
      "title": "iOS 26.5 beta is here, but there’s still no sign of new Siri",
      "summary": "Macworld The 26.4 updates brought with them a number of improvements across the various operating systems and Apple’s included apps. But they didn’t bring the expected, long overdue improvements to Siri: A new foundation model, on-screen awareness, personal context, and actions across apps. Recent rumors rumors make it seem unlikely that those things will appear before the big OS 27 updates in the fall, for which Apple is targeting even bigger Apple Intelligence upgrades. There was some hope tha",
      "url": "https://www.macworld.com/article/3102432/ios-26-5-beta-1-is-available-now.html",
      "source_name": "Macworld.com",
      "topic": "technology",
      "scores": {
        "importance": 79,
        "novelty": 0,
        "confidence": 85,
        "user_fit": 75
      },
      "why_it_matters": "",
      "tags": []
    },
    {
      "title": "TotalEnergies, NEO NEXT complete merger of UK oil and gas assets",
      "summary": "",
      "url": "https://finance.yahoo.com/sectors/energy/articles/totalenergies-neo-next-complete-merger-114426790.html",
      "source_name": "Yahoo Finance",
      "topic": "business_finance",
      "scores": {
        "importance": 70,
        "novelty": 0,
        "confidence": 65,
        "user_fit": 85
      },
      "why_it_matters": "",
      "tags": []
    },
    {
      "title": "Palantir Is Down 29% From Its High. Here's What Every Investor Needs to Know Right Now.",
      "summary": "",
      "url": "https://finance.yahoo.com/markets/stocks/articles/palantir-down-29-high-heres-113500322.html",
      "source_name": "Yahoo Finance",
      "topic": "business_finance",
      "scores": {
        "importance": 70,
        "novelty": 0,
        "confidence": 65,
        "user_fit": 85
      },
      "why_it_matters": "",
      "tags": []
    },
    {
      "title": "Astronomers determine the fate of a double white dwarf binary",
      "summary": "Utilizing the stellar evolution code named Modules for Experiments in Stellar Astrophysics (MESA), Chinese astronomers have investigated the evolution of a recently discovered ultra-compact double white dwarf binary system known as ATLAS J1138-5139. Results of this study, published March 20 on the arXiv pre-print server, allowed the researchers to determine the fate of this system.",
      "url": "https://phys.org/news/2026-03-astronomers-fate-white-dwarf-binary.html",
      "source_name": "Phys.org - latest science and technology news stories",
      "topic": "science",
      "scores": {
        "importance": 57,
        "novelty": 0,
        "confidence": 85,
        "user_fit": 45
      },
      "why_it_matters": "",
      "tags": []
    }
  ]
}